mnd_qtutils/__init__.py
mnd_qtutils/aspect_ratio_image.py
mnd_qtutils/cancellable_task.py
mnd_qtutils/cancellable_task_dialog.py
mnd_qtutils/cancellable_task_dialog_ui.py
mnd_qtutils/float_slider.py
mnd_qtutils/image_edit_layout.py
mnd_qtutils/image_edit_widget.py
mnd_qtutils/qtutils.py
mnd_qtutils-0.1.9.dist-info/LICENSE
mnd_qtutils-0.1.9.dist-info/METADATA
mnd_qtutils-0.1.9.dist-info/WHEEL
mnd_qtutils-0.1.9.dist-info/top_level.txt
mnd_qtutils-0.1.9.dist-info/RECORD
