Metadata-Version: 2.1
Name: mnd-qtutils
Version: 0.1.9
Summary: Utility functions for Qt (PySide2)
Home-page: https://github.com/mnicolas94/mnd_qtutils
Author: Miguel Nicolás-Díaz
Author-email: miguelcok27@gmail.com
License: UNKNOWN
Platform: UNKNOWN
Classifier: Programming Language :: Python :: 3
Classifier: License :: OSI Approved :: MIT License
Classifier: Operating System :: OS Independent
Classifier: Development Status :: 3 - Alpha
Classifier: Intended Audience :: Developers
Requires-Python: >=3.6
License-File: LICENSE
Requires-Dist: mnd-utils
Requires-Dist: numpy
Requires-Dist: opencv-python
Requires-Dist: PySide2
Requires-Dist: qimage2ndarray
